odoo/addons/purchase_report_hide_line/README.rst
odoo/addons/purchase_report_hide_line/__init__.py
odoo/addons/purchase_report_hide_line/__manifest__.py
odoo/addons/purchase_report_hide_line/description/icon.png
odoo/addons/purchase_report_hide_line/description/icon.svg
odoo/addons/purchase_report_hide_line/i18n/es.po
odoo/addons/purchase_report_hide_line/i18n/it.po
odoo/addons/purchase_report_hide_line/i18n/purchase_report_hide_line.pot
odoo/addons/purchase_report_hide_line/models/__init__.py
odoo/addons/purchase_report_hide_line/models/purchase_order_line.py
odoo/addons/purchase_report_hide_line/models/res_company.py
odoo/addons/purchase_report_hide_line/models/res_config_settings.py
odoo/addons/purchase_report_hide_line/readme/CONFIGURE.md
odoo/addons/purchase_report_hide_line/readme/CONTRIBUTORS.md
odoo/addons/purchase_report_hide_line/readme/DESCRIPTION.md
odoo/addons/purchase_report_hide_line/readme/USAGE.md
odoo/addons/purchase_report_hide_line/static/description/icon.png
odoo/addons/purchase_report_hide_line/static/description/icon.svg
odoo/addons/purchase_report_hide_line/tests/__init__.py
odoo/addons/purchase_report_hide_line/tests/test_purchase_report_hide_line.py
odoo/addons/purchase_report_hide_line/views/purchase_order_views.xml
odoo/addons/purchase_report_hide_line/views/report_purchase.xml
odoo/addons/purchase_report_hide_line/views/res_config_settings.xml
odoo_addon_purchase_report_hide_line-17.0.1.0.0.3.dist-info/METADATA
odoo_addon_purchase_report_hide_line-17.0.1.0.0.3.dist-info/WHEEL
odoo_addon_purchase_report_hide_line-17.0.1.0.0.3.dist-info/top_level.txt
odoo_addon_purchase_report_hide_line-17.0.1.0.0.3.dist-info/RECORD
